{
  "20,10": {
    "SourceVersionHash": "Q8itOacTXUSP/ax9k0WXzuJNumk=",
    "VersionHash": "n7dzqebjOU4zLkp11I/9eMM5kLM="
  },
  "21,10": {
    "SourceVersionHash": "Q8itOacTXUSP/ax9k0WXzuJNumk=",
    "VersionHash": "n7dzqebjOU4zLkp11I/9eMM5kLM="
  },
  "20,11": {
    "SourceVersionHash": "Q8itOacTXUSP/ax9k0WXzuJNumk=",
    "VersionHash": "n7dzqebjOU4zLkp11I/9eMM5kLM="
  },
  "21,11": {
    "SourceVersionHash": "Q8itOacTXUSP/ax9k0WXzuJNumk=",
    "VersionHash": "Z70OOpLgg1Wfshq0iepBW4XNmmE="
  },
  "22,10": {
    "SourceVersionHash": "Q8itOacTXUSP/ax9k0WXzuJNumk=",
    "VersionHash": "Z70OOpLgg1Wfshq0iepBW4XNmmE="
  },
  "23,10": {
    "SourceVersionHash": "Q8itOacTXUSP/ax9k0WXzuJNumk=",
    "VersionHash": "Z70OOpLgg1Wfshq0iepBW4XNmmE="
  },
  "22,11": {
    "SourceVersionHash": "Q8itOacTXUSP/ax9k0WXzuJNumk=",
    "VersionHash": "wwOJhfQLFm/lZoozlAW814sTHzQ="
  },
  "23,11": {
    "SourceVersionHash": "Q8itOacTXUSP/ax9k0WXzuJNumk=",
    "VersionHash": "wwOJhfQLFm/lZoozlAW814sTHzQ="
  },
  "24,10": {
    "SourceVersionHash": "Q8itOacTXUSP/ax9k0WXzuJNumk=",
    "VersionHash": "wwOJhfQLFm/lZoozlAW814sTHzQ="
  },
  "25,10": {
    "SourceVersionHash": "Q8itOacTXUSP/ax9k0WXzuJNumk=",
    "VersionHash": "6EWpvZm8QzZiBeXutIoBXQkRStY="
  },
  "24,11": {
    "SourceVersionHash": "Q8itOacTXUSP/ax9k0WXzuJNumk=",
    "VersionHash": "6EWpvZm8QzZiBeXutIoBXQkRStY="
  },
  "25,11": {
    "SourceVersionHash": "Q8itOacTXUSP/ax9k0WXzuJNumk=",
    "VersionHash": "6EWpvZm8QzZiBeXutIoBXQkRStY="
  },
  "26,10": {
    "SourceVersionHash": "Q8itOacTXUSP/ax9k0WXzuJNumk=",
    "VersionHash": "6EWpvZm8QzZiBeXutIoBXQkRStY="
  },
  "27,10": {
    "SourceVersionHash": "Q8itOacTXUSP/ax9k0WXzuJNumk=",
    "VersionHash": "iHIfQofrYc2ll4N85DBuGKBKE0M="
  },
  "26,11": {
    "SourceVersionHash": "Q8itOacTXUSP/ax9k0WXzuJNumk=",
    "VersionHash": "iHIfQofrYc2ll4N85DBuGKBKE0M="
  },
  "27,11": {
    "SourceVersionHash": "Q8itOacTXUSP/ax9k0WXzuJNumk=",
    "VersionHash": "iHIfQofrYc2ll4N85DBuGKBKE0M="
  },
  "28,10": {
    "SourceVersionHash": "Q8itOacTXUSP/ax9k0WXzuJNumk=",
    "VersionHash": "3KAMxdepq2rrvuKnOMLzqX4h2eU="
  },
  "29,10": {
    "SourceVersionHash": "Q8itOacTXUSP/ax9k0WXzuJNumk=",
    "VersionHash": "3KAMxdepq2rrvuKnOMLzqX4h2eU="
  },
  "28,11": {
    "SourceVersionHash": "Q8itOacTXUSP/ax9k0WXzuJNumk=",
    "VersionHash": "3KAMxdepq2rrvuKnOMLzqX4h2eU="
  },
  "29,11": {
    "SourceVersionHash": "Q8itOacTXUSP/ax9k0WXzuJNumk=",
    "VersionHash": "3KAMxdepq2rrvuKnOMLzqX4h2eU="
  },
  "20,12": {
    "SourceVersionHash": "7BVuxp/wfDynCp3nd+PT3JvH+6k=",
    "VersionHash": "fedMVLji1DDEY1Oxgc0p+0In1JI="
  },
  "21,12": {
    "SourceVersionHash": "7BVuxp/wfDynCp3nd+PT3JvH+6k=",
    "VersionHash": "fedMVLji1DDEY1Oxgc0p+0In1JI="
  },
  "20,13": {
    "SourceVersionHash": "7BVuxp/wfDynCp3nd+PT3JvH+6k=",
    "VersionHash": "fedMVLji1DDEY1Oxgc0p+0In1JI="
  },
  "21,13": {
    "SourceVersionHash": "7BVuxp/wfDynCp3nd+PT3JvH+6k=",
    "VersionHash": "fedMVLji1DDEY1Oxgc0p+0In1JI="
  },
  "22,12": {
    "SourceVersionHash": "7BVuxp/wfDynCp3nd+PT3JvH+6k=",
    "VersionHash": "fedMVLji1DDEY1Oxgc0p+0In1JI="
  },
  "23,12": {
    "SourceVersionHash": "7BVuxp/wfDynCp3nd+PT3JvH+6k=",
    "VersionHash": "fedMVLji1DDEY1Oxgc0p+0In1JI="
  },
  "22,13": {
    "SourceVersionHash": "7BVuxp/wfDynCp3nd+PT3JvH+6k=",
    "VersionHash": "fedMVLji1DDEY1Oxgc0p+0In1JI="
  },
  "23,13": {
    "SourceVersionHash": "7BVuxp/wfDynCp3nd+PT3JvH+6k=",
    "VersionHash": "fedMVLji1DDEY1Oxgc0p+0In1JI="
  },
  "24,12": {
    "SourceVersionHash": "7BVuxp/wfDynCp3nd+PT3JvH+6k=",
    "VersionHash": "fedMVLji1DDEY1Oxgc0p+0In1JI="
  },
  "25,12": {
    "SourceVersionHash": "7BVuxp/wfDynCp3nd+PT3JvH+6k=",
    "VersionHash": "fedMVLji1DDEY1Oxgc0p+0In1JI="
  },
  "24,13": {
    "SourceVersionHash": "7BVuxp/wfDynCp3nd+PT3JvH+6k=",
    "VersionHash": "fedMVLji1DDEY1Oxgc0p+0In1JI="
  },
  "25,13": {
    "SourceVersionHash": "7BVuxp/wfDynCp3nd+PT3JvH+6k=",
    "VersionHash": "fedMVLji1DDEY1Oxgc0p+0In1JI="
  },
  "26,12": {
    "SourceVersionHash": "Q8itOacTXUSP/ax9k0WXzuJNumk=",
    "VersionHash": "fedMVLji1DDEY1Oxgc0p+0In1JI="
  },
  "27,12": {
    "SourceVersionHash": "Q8itOacTXUSP/ax9k0WXzuJNumk=",
    "VersionHash": "ifxmi9f3B3kbDdJTvLPT+XoMDxM="
  },
  "26,13": {
    "SourceVersionHash": "Q8itOacTXUSP/ax9k0WXzuJNumk=",
    "VersionHash": "ifxmi9f3B3kbDdJTvLPT+XoMDxM="
  },
  "27,13": {
    "SourceVersionHash": "Q8itOacTXUSP/ax9k0WXzuJNumk=",
    "VersionHash": "ifxmi9f3B3kbDdJTvLPT+XoMDxM="
  },
  "28,12": {
    "SourceVersionHash": "Q8itOacTXUSP/ax9k0WXzuJNumk=",
    "VersionHash": "ifxmi9f3B3kbDdJTvLPT+XoMDxM="
  },
  "29,12": {
    "SourceVersionHash": "Q8itOacTXUSP/ax9k0WXzuJNumk=",
    "VersionHash": "ifxmi9f3B3kbDdJTvLPT+XoMDxM="
  },
  "28,13": {
    "SourceVersionHash": "Q8itOacTXUSP/ax9k0WXzuJNumk=",
    "VersionHash": "ifxmi9f3B3kbDdJTvLPT+XoMDxM="
  },
  "29,13": {
    "SourceVersionHash": "Q8itOacTXUSP/ax9k0WXzuJNumk=",
    "VersionHash": "ifxmi9f3B3kbDdJTvLPT+XoMDxM="
  },
  "20,16": {
    "SourceVersionHash": "4rQNY9ZofwoFLiK7O5jcR96xQW4=",
    "VersionHash": "anp8h+gWKY61GamdRGwJimWtM4w="
  },
  "21,16": {
    "SourceVersionHash": "4rQNY9ZofwoFLiK7O5jcR96xQW4=",
    "VersionHash": "anp8h+gWKY61GamdRGwJimWtM4w="
  },
  "20,17": {
    "SourceVersionHash": "4rQNY9ZofwoFLiK7O5jcR96xQW4=",
    "VersionHash": "anp8h+gWKY61GamdRGwJimWtM4w="
  },
  "21,17": {
    "SourceVersionHash": "4rQNY9ZofwoFLiK7O5jcR96xQW4=",
    "VersionHash": "anp8h+gWKY61GamdRGwJimWtM4w="
  },
  "26,16": {
    "SourceVersionHash": "4rQNY9ZofwoFLiK7O5jcR96xQW4=",
    "VersionHash": "anp8h+gWKY61GamdRGwJimWtM4w="
  },
  "27,16": {
    "SourceVersionHash": "4rQNY9ZofwoFLiK7O5jcR96xQW4=",
    "VersionHash": "anp8h+gWKY61GamdRGwJimWtM4w="
  },
  "26,17": {
    "SourceVersionHash": "4rQNY9ZofwoFLiK7O5jcR96xQW4=",
    "VersionHash": "anp8h+gWKY61GamdRGwJimWtM4w="
  },
  "27,17": {
    "SourceVersionHash": "4rQNY9ZofwoFLiK7O5jcR96xQW4=",
    "VersionHash": "anp8h+gWKY61GamdRGwJimWtM4w="
  }
}