{
  "16,-10": {
    "SourceVersionHash": "5D0Cvw1hHPKOb/ZHIasqmdGL1e0=",
    "VersionHash": "exLQ+F9AdRukU2kF8Mfha7AhnFo="
  },
  "11,-9": {
    "SourceVersionHash": "uRkKpFl9bCr7Y4IKbPhM4Tb4stE=",
    "VersionHash": "exLQ+F9AdRukU2kF8Mfha7AhnFo="
  },
  "13,-9": {
    "SourceVersionHash": "uRkKpFl9bCr7Y4IKbPhM4Tb4stE=",
    "VersionHash": "exLQ+F9AdRukU2kF8Mfha7AhnFo="
  },
  "18,-9": {
    "SourceVersionHash": "uRkKpFl9bCr7Y4IKbPhM4Tb4stE=",
    "VersionHash": "exLQ+F9AdRukU2kF8Mfha7AhnFo="
  },
  "10,-7": {
    "SourceVersionHash": "pzqBndiIgoev2ZDvtMhjWrYhe+M=",
    "VersionHash": "CcP51U9jrnKtUaZw8YJEoqL70ik="
  },
  "13,-7": {
    "SourceVersionHash": "pzqBndiIgoev2ZDvtMhjWrYhe+M=",
    "VersionHash": "CcP51U9jrnKtUaZw8YJEoqL70ik="
  },
  "16,-7": {
    "SourceVersionHash": "pzqBndiIgoev2ZDvtMhjWrYhe+M=",
    "VersionHash": "CcP51U9jrnKtUaZw8YJEoqL70ik="
  },
  "18,-6": {
    "SourceVersionHash": "YB/1CRhqFDhReC5Rgn91E0PzSjU=",
    "VersionHash": "CcP51U9jrnKtUaZw8YJEoqL70ik="
  },
  "11,-5": {
    "SourceVersionHash": "8+KoYUYp1hAOhSWukw18YNx4ln0=",
    "VersionHash": "kvfqiUlkus7pMqDJ3IMcOJgMrJI="
  },
  "12,-5": {
    "SourceVersionHash": "eHtLbRsD6e0DCvXlRGMiWW2Gbt8=",
    "VersionHash": "kvfqiUlkus7pMqDJ3IMcOJgMrJI="
  },
  "15,-5": {
    "SourceVersionHash": "eHtLbRsD6e0DCvXlRGMiWW2Gbt8=",
    "VersionHash": "kvfqiUlkus7pMqDJ3IMcOJgMrJI="
  },
  "18,-4": {
    "SourceVersionHash": "6Qh7kCHpzT1Pu9VTUr8qHJLZcFE=",
    "VersionHash": "kvfqiUlkus7pMqDJ3IMcOJgMrJI="
  },
  "13,-3": {
    "SourceVersionHash": "nIbzbxpvGXaP/3dluEQfeVoEgLo=",
    "VersionHash": "NgLkWG6op4pXXTx56bTZ46SEHR4="
  },
  "18,-3": {
    "SourceVersionHash": "nIbzbxpvGXaP/3dluEQfeVoEgLo=",
    "VersionHash": "NgLkWG6op4pXXTx56bTZ46SEHR4="
  },
  "11,-2": {
    "SourceVersionHash": "mbrOYtOv/dQf+JdFM3BhxZmKGSE=",
    "VersionHash": "g2PmTrxmZ0Gxa/FwLcXxlZln7rs="
  },
  "16,-2": {
    "SourceVersionHash": "mbrOYtOv/dQf+JdFM3BhxZmKGSE=",
    "VersionHash": "g2PmTrxmZ0Gxa/FwLcXxlZln7rs="
  }
}